{
	"configurations" : 
	[
		{
			"directories" : 
			[
				{
					"build" : ".",
					"hasInstallRule" : true,
					"jsonFile" : "directory-.-Debug-316e60aec4b1a903527f.json",
					"minimumCMakeVersion" : 
					{
						"string" : "3.16"
					},
					"projectIndex" : 0,
					"source" : ".",
					"targetIndexes" : 
					[
						0
					]
				}
			],
			"name" : "Debug",
			"projects" : 
			[
				{
					"directoryIndexes" : 
					[
						0
					],
					"name" : "DesafioBorrador",
					"targetIndexes" : 
					[
						0
					]
				}
			],
			"targets" : 
			[
				{
					"directoryIndex" : 0,
					"id" : "DesafioBorrador::@6890427a1f51a3e7e1df",
					"jsonFile" : "target-DesafioBorrador-Debug-d2016167f8bc59f5825d.json",
					"name" : "DesafioBorrador",
					"projectIndex" : 0
				}
			]
		}
	],
	"kind" : "codemodel",
	"paths" : 
	{
		"build" : "C:/Users/MekaNet/Desktop/UdeA/Semestre 3/Informatica II/Desafio Borrador/DesafioBorrador/build/Desktop_Qt_6_9_2_MinGW_64_bit-Debug",
		"source" : "C:/Users/MekaNet/Desktop/UdeA/Semestre 3/Informatica II/Desafio Borrador/DesafioBorrador"
	},
	"version" : 
	{
		"major" : 2,
		"minor" : 7
	}
}
